simpleci/__init__.py
simpleci/cli.py
simpleci/simpleci.py
simpleci_nfarrokhian-0.2.5.dist-info/AUTHORS.rst
simpleci_nfarrokhian-0.2.5.dist-info/LICENSE
simpleci_nfarrokhian-0.2.5.dist-info/METADATA
simpleci_nfarrokhian-0.2.5.dist-info/WHEEL
simpleci_nfarrokhian-0.2.5.dist-info/entry_points.txt
simpleci_nfarrokhian-0.2.5.dist-info/top_level.txt
simpleci_nfarrokhian-0.2.5.dist-info/RECORD
