Metadata-Version: 2.1
Name: simpleci-nfarrokhian
Version: 0.2.5
Summary: generates concentration curves from ordered data and calculates concentration indices (ACI and RCI)
Home-page: https://github.com/nfarrokhian/simpleci
Author: Nathan Farrokhian
Author-email: n.farrokhian@gmail.com
License: MIT license
Keywords: simpleci
Platform: UNKNOWN
Classifier: Development Status :: 2 - Pre-Alpha
Classifier: Intended Audience :: Developers
Classifier: License :: OSI Approved :: MIT License
Classifier: Natural Language :: English
Classifier: Programming Language :: Python :: 3
Classifier: Programming Language :: Python :: 3.6
Classifier: Programming Language :: Python :: 3.7
Classifier: Programming Language :: Python :: 3.8
Requires-Python: >=3.6
License-File: LICENSE
License-File: AUTHORS.rst
Requires-Dist: Click (>=7.0)
